README.rst
setup.py
xe/__init__.py
xe/do.py
xe/models.py
xe/run.py
xe.egg-info/PKG-INFO
xe.egg-info/SOURCES.txt
xe.egg-info/dependency_links.txt
xe.egg-info/entry_points.txt
xe.egg-info/pbr.json
xe.egg-info/requires.txt
xe.egg-info/top_level.txt
xe/cmds/__init__.py
xe/cmds/bootstrap.py
xe/cmds/manage.py
xe/cmds/test.py
xe/cmds/testing.py