Metadata-Version: 1.0
Name: xe
Version: 0.2
Summary: Reliably manage your python dev environment.
Home-page: http://github.com/ionrock/xe
Author: Eric Larson
Author-email: eric@ionrock.org
License: UNKNOWN
Platform: UNKNOWN
